space_objects/__init__.py
space_objects/base/__init__.py
space_objects/base/decorators.py
space_objects/base/models.py
space_objects/base/outputs.py
space_objects/base/spo_types.py
space_objects/matplotlib/__init__.py
space_objects/matplotlib/compass.py
space_objects/models.py
space_objects/scripts/__init__.py
space_objects/scripts/cli.py
space_objects/scripts/load_tle.py
space_objects/scripts/planets.py
space_objects/scripts/satellites.py
space_objects/settings.py
space_objects-1.5.0.dist-info/entry_points.txt
space_objects-1.5.0.dist-info/LICENSE
space_objects-1.5.0.dist-info/WHEEL
space_objects-1.5.0.dist-info/METADATA
space_objects-1.5.0.dist-info/RECORD
