Metadata-Version: 2.1
Name: space-objects
Version: 1.5.0
Summary: wrapper lib around the skyfield package
Author: larrieu olivier
Author-email: larrieuolivierad@gmail.com
Requires-Python: >=3.10,<4.0
Classifier: Programming Language :: Python :: 3
Classifier: Programming Language :: Python :: 3.10
Classifier: Programming Language :: Python :: 3.11
Requires-Dist: click (>=8.1.3,<9.0.0)
Requires-Dist: skyfield (>=1.45,<2.0)
Requires-Dist: tabulate (>=0.9.0,<0.10.0)
